{
	"info": {
		"_postman_id": "80340a55-79a8-48be-80a7-a8c778f15943",
		"name": "Swapi",
		"schema": "https://schema.getpostman.com/json/collection/v2.1.0/collection.json"
	},
	"item": [
		{
			"name": "People",
			"request": {
				"method": "GET",
				"header": [],
				"url": {
					"raw": "https://swapi.dev/api/people/83",
					"protocol": "https",
					"host": [
						"swapi",
						"dev"
					],
					"path": [
						"api",
						"people",
						"83"
					]
				}
			},
			"response": []
		},
		{
			"name": "Films",
			"request": {
				"method": "GET",
				"header": [],
				"url": {
					"raw": "https://swapi.dev/api/films/1/",
					"protocol": "https",
					"host": [
						"swapi",
						"dev"
					],
					"path": [
						"api",
						"films",
						"1",
						""
					]
				}
			},
			"response": []
		},
		{
			"name": "Starships",
			"request": {
				"method": "GET",
				"header": [],
				"url": {
					"raw": "https://swapi.dev/api/starships/9/",
					"protocol": "https",
					"host": [
						"swapi",
						"dev"
					],
					"path": [
						"api",
						"starships",
						"9",
						""
					]
				}
			},
			"response": []
		},
		{
			"name": "Vehicles",
			"request": {
				"method": "GET",
				"header": [],
				"url": {
					"raw": "https://swapi.dev/api/vehicles/4/",
					"protocol": "https",
					"host": [
						"swapi",
						"dev"
					],
					"path": [
						"api",
						"vehicles",
						"4",
						""
					]
				}
			},
			"response": []
		},
		{
			"name": "Species",
			"request": {
				"method": "GET",
				"header": [],
				"url": {
					"raw": "https://swapi.dev/api/species/3/",
					"protocol": "https",
					"host": [
						"swapi",
						"dev"
					],
					"path": [
						"api",
						"species",
						"3",
						""
					]
				}
			},
			"response": []
		}
	]
}